subtypes/__init__.py
subtypes/color.py
subtypes/datetime.py
subtypes/dict.py
subtypes/enums.py
subtypes/frame.py
subtypes/http.py
subtypes/lazy.py
subtypes/list.py
subtypes/markup.py
subtypes/namespace.py
subtypes/process.py
subtypes/singleton.py
subtypes/str.py
subtypes/translator.py
pysubtypes-0.3.18.dist-info/LICENSE
pysubtypes-0.3.18.dist-info/METADATA
pysubtypes-0.3.18.dist-info/WHEEL
pysubtypes-0.3.18.dist-info/top_level.txt
pysubtypes-0.3.18.dist-info/RECORD
