Metadata-Version: 2.1
Name: pysubtypes
Version: 0.3.18
Summary: Provides subclasses for common python types with additional functionality and convenience methods.
Home-page: https://github.com/matthewgdv/subtypes
Author: Matt GdV
Author-email: matthewgdv@gmail.com
License: MIT
Platform: UNKNOWN
Classifier: Development Status :: 3 - Alpha
Classifier: Intended Audience :: Developers
Classifier: Programming Language :: Python :: 3.8
